bugseq_client/__init__.py
bugseq_client/openapi_client_README.md
bugseq_client/auth/__init__.py
bugseq_client/auth/session.py
bugseq_client/auth/web_auth.py
bugseq_client/auth/storage/__init__.py
bugseq_client/auth/storage/abstract.py
bugseq_client/auth/storage/default.py
bugseq_client/auth/storage/keyring.py
bugseq_client/auth/storage/local.py
bugseq_client/openapi_client/__init__.py
bugseq_client/openapi_client/api_client.py
bugseq_client/openapi_client/api_response.py
bugseq_client/openapi_client/configuration.py
bugseq_client/openapi_client/exceptions.py
bugseq_client/openapi_client/rest.py
bugseq_client/openapi_client/api/__init__.py
bugseq_client/openapi_client/api/billing_api.py
bugseq_client/openapi_client/api/files_api.py
bugseq_client/openapi_client/api/jobs_api.py
bugseq_client/openapi_client/api/users_api.py
bugseq_client/openapi_client/docs/BillingAccountSampleCreditResponse.md
bugseq_client/openapi_client/docs/BillingApi.md
bugseq_client/openapi_client/docs/FileCreateS3Request.md
bugseq_client/openapi_client/docs/FileDownloadResponse.md
bugseq_client/openapi_client/docs/FileInitUploadS3Response.md
bugseq_client/openapi_client/docs/FileMultipartChunkInitUploadRequest.md
bugseq_client/openapi_client/docs/FileMultipartUploadCompleteRequest.md
bugseq_client/openapi_client/docs/FilesApi.md
bugseq_client/openapi_client/docs/HTTPValidationError.md
bugseq_client/openapi_client/docs/JobRunFileResponse.md
bugseq_client/openapi_client/docs/JobRunListResponse.md
bugseq_client/openapi_client/docs/JobRunResponse.md
bugseq_client/openapi_client/docs/JobRunResultsResponse.md
bugseq_client/openapi_client/docs/JobRunSubmitRequest.md
bugseq_client/openapi_client/docs/JobRunSubmitRequestUserProvidedMetadataInnerValue.md
bugseq_client/openapi_client/docs/JobRunSubmitResponse.md
bugseq_client/openapi_client/docs/JobStatus.md
bugseq_client/openapi_client/docs/JobsApi.md
bugseq_client/openapi_client/docs/Kit.md
bugseq_client-0.1.6.dist-info/METADATA
bugseq_client-0.1.6.dist-info/WHEEL
bugseq_client-0.1.6.dist-info/licenses/LICENSE
bugseq_client-0.1.6.dist-info/RECORD
