Metadata-Version: 2.4
Name: bugseq-client
Version: 0.1.6
Summary: Python client for BugSeq (https://bugseq.com)
Project-URL: Homepage, https://gitlab.com/bugseq-open/bugseq-client-py
Project-URL: Issues, https://gitlab.com/bugseq-open/bugseq-client-py/-/issues
Author-email: Josh Chorlton <josh@bugseq.com>
License: Apache 2.0
License-File: LICENSE
Requires-Python: >=3.11
Requires-Dist: authlib>=1.6.1
Requires-Dist: keyring>=25.6.0
Requires-Dist: pydantic>=2.11.7
Requires-Dist: python-dateutil>=2.9.0
Requires-Dist: requests>=2.32.4
